README.md
setup.py
davemercer/__init__.py
davemercer/steamworkshop/__init__.py
davemercer/steamworkshop/api.py
davemercer/steamworkshop/app.py
davemercer/steamworkshop/exceptions.py
davemercer/steamworkshop/models.py
pyplanet_steamworkshop.egg-info/PKG-INFO
pyplanet_steamworkshop.egg-info/SOURCES.txt
pyplanet_steamworkshop.egg-info/dependency_links.txt
pyplanet_steamworkshop.egg-info/requires.txt
pyplanet_steamworkshop.egg-info/top_level.txt