Metadata-Version: 2.1
Name: pyplanet-steamworkshop
Version: 1.0.0
Summary: PyPlanet Steam Workshop
Home-page: https://github.com/Deivmercer/PyPlanetSteamWorkshop
Author: Davide Costantini
Author-email: davemercerdave@gmail.com
